battlemaster/__init__.py
battlemaster/rules/__init__.py
battlemaster/rules/tables/__init__.py
battlemaster/rules/tables/hex_type.py
battlemaster/rules/tables/turn_phase.py
battlemaster-0.1.2.dist-info/LICENSE.txt
battlemaster-0.1.2.dist-info/METADATA
battlemaster-0.1.2.dist-info/WHEEL
battlemaster-0.1.2.dist-info/top_level.txt
battlemaster-0.1.2.dist-info/RECORD
