Metadata-Version: 2.1
Name: battlemaster
Version: 0.1.2
Summary: A library for a game of armored combat.
Home-page: https://github.com/johnnystarr/battlemaster
Author: Johnny Starr
License-File: LICENSE.txt
